ollama_cli/.gitignore
ollama_cli/__init__.py
ollama_cli/ollama_cli_main.py
ollama_cli-0.2.0.dist-info/METADATA
ollama_cli-0.2.0.dist-info/WHEEL
ollama_cli-0.2.0.dist-info/entry_points.txt
ollama_cli-0.2.0.dist-info/licenses/LICENSE
ollama_cli-0.2.0.dist-info/RECORD
