Metadata-Version: 2.4
Name: ollama-cli
Version: 0.2.0
Summary: Simple command line tool that reads a text from stdin and pipes it to Ollama. One can set all Ollama options on commandline as well as define termination criteria in terms of maximum number of lines, paragraphs, or repeated lines.
Project-URL: Homepage, https://github.com/DrMicrobit/ollama-cli
Project-URL: GitHub, https://github.com/DrMicrobit/ollama-cli
Project-URL: Issues, https://github.com/DrMicrobit/ollama-cli/issues
Author-email: Bastien Chevreux <bach@chevreux.org>
License-Expression: MIT
License-File: LICENSE
Classifier: Development Status :: 5 - Production/Stable
Classifier: Environment :: Console
Classifier: Intended Audience :: End Users/Desktop
Classifier: License :: OSI Approved :: MIT License
Classifier: Operating System :: OS Independent
Classifier: Programming Language :: Python :: 3
Requires-Python: >=3.13
Requires-Dist: dm-ollamalib>=0.2.0
Requires-Dist: dm-streamvalve>=0.1.1
Requires-Dist: httpx>=0.28.1
Requires-Dist: ollama>=0.4.8
